{
    "$schema": "https://schema.management.azure.com/schemas/2015-01-01/deploymentParameters.json#",
    "contentVersion": "1.0.0.0",
    "parameters": { 
        "location": {
            "value": "uksouth"
        },
        "environmentName": {
            "value": "dev"
        },
        "projectName": {
            "value": "ais-demo-project"
        },
        "logicAppName": {
            "value": "ais-demo"
        },
        "appServicePlanName": {
            "value": "asp-ais-demo-maelzaye"
        },
        "storageName": {
            "value": "sa-ais-demo-maelzaye"
        },
        "kind": {
            "value": "StorageV2"
        },
        "skuName": {
            "value": "Standard_LRS"
        },
        "skuTier": {
            "value": "Standard"
          }
        }
    }